README.md
setup.py
torchvggish/__init__.py
torchvggish/mel_features.py
torchvggish/torchvggish.py
torchvggish/vggish_input.py
torchvggish/vggish_params.py
torchvggish.egg-info/PKG-INFO
torchvggish.egg-info/SOURCES.txt
torchvggish.egg-info/dependency_links.txt
torchvggish.egg-info/requires.txt
torchvggish.egg-info/top_level.txt